xcofdk_se-1.0.dist-info/top_level.txt
xcofdk_se-1.0.dist-info/METADATA
xcofdk_se-1.0.dist-info/WHEEL
xcofdk_se-1.0.dist-info/RECORD
xcofdk_se-1.0.data/scripts/run_xcogen.py
xcofdk/LICENSE.txt
xcofdk/README.rst
xcofdk/fwapi/__init__.py
xcofdk/fwapi/xcounit/mainxcounit.py
xcofdk/fwapi/xcounit/__init__.py
xcofdk/fwapi/xcounit/xcounitprf.py
xcofdk/fwapi/xcounit/xcouniterr.py
xcofdk/fwapi/xcounit/xcounit.py
xcofdk/fwapi/xcounit/xlogif.py
xcofdk/_xcofwa/fwFHL.cpython-311-x86_64-linux-gnu.so
xcofdk/_xcofwa/fwFHK.cpython-311-x86_64-linux-gnu.so
xcofdk/tests/myMainXcounit.py
xcofdk/tests/myXcounit.py
xcofdk/tests/__init__.py
xcofdk/tests/test_xcofdkse.py
xcofdk/tests/startXcoFDK.py
xcofdk/_xcofw/fwDFN.cpython-311-x86_64-linux-gnu.so
xcofdk/_xcofw/fwCKN.cpython-311-x86_64-linux-gnu.so
xcofdk/_xcofw/fwCKP.cpython-311-x86_64-linux-gnu.so
xcofdk/_xcofw/fwDFL.cpython-311-x86_64-linux-gnu.so
xcofdk/_xcofw/fwCIK.cpython-311-x86_64-linux-gnu.so
xcofdk/_xcofw/fwCFG.cpython-311-x86_64-linux-gnu.so
xcofdk/_xcofw/fwCFK.cpython-311-x86_64-linux-gnu.so
xcofdk/_xcofw/fwCFM.cpython-311-x86_64-linux-gnu.so
xcofdk/_xcofw/fwCIJ.cpython-311-x86_64-linux-gnu.so
xcofdk/_xcofw/fwDFH.cpython-311-x86_64-linux-gnu.so
xcofdk/_xcofw/fwCEN.cpython-311-x86_64-linux-gnu.so
xcofdk/_xcofw/fwCNN.cpython-311-x86_64-linux-gnu.so
xcofdk/_xcofw/fwCHP.cpython-311-x86_64-linux-gnu.so
xcofdk/_xcofw/fwCLP.cpython-311-x86_64-linux-gnu.so
xcofdk/_xcofw/fwCKL.cpython-311-x86_64-linux-gnu.so
xcofdk/_xcofw/fwCNG.cpython-311-x86_64-linux-gnu.so
xcofdk/_xcofw/fwCIL.cpython-311-x86_64-linux-gnu.so
xcofdk/_xcofw/fwDEL.cpython-311-x86_64-linux-gnu.so
xcofdk/_xcofw/fwCNM.cpython-311-x86_64-linux-gnu.so
xcofdk/_xcofw/fwCLI.cpython-311-x86_64-linux-gnu.so
xcofdk/_xcofw/fwCIP.cpython-311-x86_64-linux-gnu.so
xcofdk/_xcofw/fwDEJ.cpython-311-x86_64-linux-gnu.so
xcofdk/_xcofw/fwCNP.cpython-311-x86_64-linux-gnu.so
xcofdk/_xcofw/fwDFK.cpython-311-x86_64-linux-gnu.so
xcofdk/_xcofw/fwDFI.cpython-311-x86_64-linux-gnu.so
xcofdk/_xcofw/fwCKI.cpython-311-x86_64-linux-gnu.so
xcofdk/_xcofw/fwCJO.cpython-311-x86_64-linux-gnu.so
