Metadata-Version: 2.1
Name: xcofdk-se
Version: 1.0
Summary: XCOFDK Starter Edition (SE) is a runtime environment to provide multithreading and life cycle management to programs.
Home-page: https://www.xcofdk.de/
Author: Farzad Safa
Author-email: farzad.safa@xcofdk.de
License: Free To Use But Restricted
Platform: Linux
Classifier: Development Status :: 4 - Beta
Classifier: License :: Free To Use But Restricted
Classifier: Natural Language :: English
Classifier: Operating System :: POSIX :: Linux
Classifier: Programming Language :: Python :: 3.11
Classifier: Intended Audience :: Developers
Classifier: Topic :: Software Development
Classifier: Topic :: Software Development :: Libraries :: Application Frameworks
Classifier: Topic :: Software Development :: Code Generators
Requires-Python: ==3.11
Requires-Dist: jinja2
